steemconnect/__init__.py
steemconnect/backends.py
social_auth_steemconnect-0.0.3.dist-info/LICENSE
social_auth_steemconnect-0.0.3.dist-info/METADATA
social_auth_steemconnect-0.0.3.dist-info/WHEEL
social_auth_steemconnect-0.0.3.dist-info/top_level.txt
social_auth_steemconnect-0.0.3.dist-info/RECORD
