Metadata-Version: 2.1
Name: social-auth-steemconnect
Version: 0.0.3
Summary: SteemConnect backend for python-social-auth.
Home-page: https://github.com/wise-team/python-social-auth-steemconnect
Author: Krzysztof @noisy Szumny
Author-email: noisy.pl@gmail.com
License: LICENSE
Keywords: django social auth oauth2 social-auth steem steemconnect steemit
Platform: UNKNOWN
Classifier: Development Status :: 3 - Alpha
Classifier: Intended Audience :: Developers
Classifier: License :: OSI Approved :: MIT License
Classifier: Programming Language :: Python :: 3.4
Requires-Dist: python-social-auth
